smv/__init__.py
smv/csv_attributes.py
smv/datasetmgr.py
smv/datasetrepo.py
smv/datasetresolver.py
smv/dqm.py
smv/error.py
smv/functions.py
smv/helpers.py
smv/historical_validators.py
smv/jprops.py
smv/matcher.py
smv/modulesvisitor.py
smv/panel.py
smv/provider.py
smv/runconfig.py
smv/runinfo.py
smv/schema_meta_ops.py
smv/smvapp.py
smv/smvappinfo.py
smv/smvconfig.py
smv/smvdriver.py
smv/smvgenericmodule.py
smv/smvhdfs.py
smv/smvinput.py
smv/smviostrategy.py
smv/smvlock.py
smv/smvmetadata.py
smv/smvmodule.py
smv/smvmodulerunner.py
smv/smvschema.py
smv/smvshell.py
smv/utils.py
smv/conn/__init__.py
smv/conn/conninfos.py
smv/conn/smvconnectioninfo.py
smv/docker/smv/bashrc
smv/docker/smv/entrypoint.sh
smv/docker/smv/hive-site.xml
smv/docker/smv/jupyter_notebook_config.py
smv/docker/smv/kernel.json
smv/docker/smv/requirements.txt
smv/docs/FAQ.md
smv/docs/RoadMap.md
smv/docs/dev/00_DevProcess/best_practice.md
smv/docs/dev/00_DevProcess/building_with_sbt.md
smv/docs/dev/00_DevProcess/create_smv_release.md
smv/docs/dev/00_DevProcess/getting_started.md
smv/docs/dev/01_OverallDesign/app_class.puml
smv/docs/dev/01_OverallDesign/smv_app_vs_context.puml
smv/docs/dev/CSV/csv_attributes.md
smv/docs/dev/DataSetMgr/DataSetMgr.md
smv/docs/dev/DataSetMgr/DataSetMgr_class.puml
smv/docs/dev/DataSetMgr/DataSetMgr_seq.puml
smv/docs/dev/DataSetMgr/psuedo_code.txt
smv/docs/dev/DataSetMgr/todo.md
smv/docs/dev/Docker/docker_versions.md
smv/docs/dev/Metadata/SmvMetadata.md
smv/docs/dev/Metadata/SmvMetadata.puml
smv/docs/dev/Migration/SmvMigrateTo1.3.md
smv/docs/dev/Migration/SmvMigrateTo1.5.md
smv/docs/dev/Migration/SmvMigrateTo1.6.md
smv/docs/dev/Python/mixins.md
smv/docs/dev/Python/overview.md
smv/docs/dev/Python/py_api_class.puml
smv/docs/dev/Python/py_api_seq.puml
smv/docs/dev/Python/reload_python_code.md
smv/docs/dev/SmvConfig/smvconfig.md
smv/docs/dev/SmvDQM/SmvDQM.md
smv/docs/dev/SmvDQM/SmvDQM.puml
smv/src/main/python/smv.egg-info/PKG-INFO
smv/src/main/python/smv.egg-info/SOURCES.txt
smv/src/main/python/smv.egg-info/dependency_links.txt
smv/src/main/python/smv.egg-info/requires.txt
smv/src/main/python/smv.egg-info/top_level.txt
smv-2.post13.dist-info/METADATA
smv-2.post13.dist-info/RECORD
smv-2.post13.dist-info/WHEEL
smv-2.post13.dist-info/top_level.txt
